setup.py
geometric_shapes/__init__.py
geometric_shapes/circle.py
geometric_shapes/rectangle.py
geometric_shapes/triangle.py
math_operations_oop.egg-info/PKG-INFO
math_operations_oop.egg-info/SOURCES.txt
math_operations_oop.egg-info/dependency_links.txt
math_operations_oop.egg-info/top_level.txt