Metadata-Version: 2.1
Name: math-operations-oop
Version: 0.1
Summary: Python package for basic mathematical operations using OOP concepts
Home-page: https://github.com/vaibhav99ghorpade/math_operations_oop
Author: Vaibhav Ghorpade
Author-email: vaibhav99ghorpade@gmail.com
Classifier: Development Status :: 3 - Alpha
Classifier: Intended Audience :: Developers
Classifier: License :: OSI Approved :: MIT License
Classifier: Programming Language :: Python :: 3
Classifier: Programming Language :: Python :: 3.6
Classifier: Programming Language :: Python :: 3.7
Classifier: Programming Language :: Python :: 3.8
Classifier: Programming Language :: Python :: 3.9
